MANIFEST.in
README.rst
setup.py
textclean/__init__.py
textclean/lookup.txt
textclean/textclean.py
textclean.egg-info/PKG-INFO
textclean.egg-info/SOURCES.txt
textclean.egg-info/dependency_links.txt
textclean.egg-info/top_level.txt