Metadata-Version: 1.0
Name: textclean
Version: 0.3.1
Summary: Handle the very famous decoding - encoding errors in Python !
Home-page: UNKNOWN
Author: Vikas Bharti
Author-email: vikas.bharti.pro@gmail.com
License: MIT
Platform: UNKNOWN
Classifier: Programming Language :: Python
Classifier: Programming Language :: Python :: 2.5
Classifier: Programming Language :: Python :: 2.6
Classifier: Programming Language :: Python :: 2.7
